TextStatistic/TextStatistic.py
TextStatistic/__init__.py
TextStatistic-1.0.6.dist-info/LICENSE.txt
TextStatistic-1.0.6.dist-info/METADATA
TextStatistic-1.0.6.dist-info/WHEEL
TextStatistic-1.0.6.dist-info/top_level.txt
TextStatistic-1.0.6.dist-info/RECORD
