Metadata-Version: 2.1
Name: TextStatistic
Version: 1.0.6
Summary: Text statistics
Home-page: https://github.com/ShadowStalker13/TextStatistics
Author: Andrew Puchkov
Author-email: andr1502puch@gmail.com
License: UNKNOWN
Platform: UNKNOWN
Classifier: Operating System :: Microsoft :: Windows :: Windows 10
Classifier: Programming Language :: Python :: 3.9
